README.md
setup.py
lounge/__init__.py
lounge/main.py
lounge.egg-info/PKG-INFO
lounge.egg-info/SOURCES.txt
lounge.egg-info/dependency_links.txt
lounge.egg-info/entry_points.txt
lounge.egg-info/requires.txt
lounge.egg-info/top_level.txt
tests/__init__.py
tests/sample.py