Metadata-Version: 2.1
Name: lounge
Version: 0.0.0
Summary: UNKNOWN
Home-page: https://github.com/Zarad1993/lounge
Author: Mohammad Albakri
Author-email: mohammad.albakri93@gmail.com
License: UNKNOWN
Platform: UNKNOWN
